quingo/__init__.py
quingo/global_config.py
quingo/install_quingoc.py
quingo/utils.py
quingo/backend/__init__.py
quingo/backend/backend_hub.py
quingo/backend/if_backend.py
quingo/backend/pyqcisim_quantumsim.py
quingo/backend/pyqcisim_tequila.py
quingo/backend/qisa.py
quingo/backend/qos.py
quingo/backend/qualesim.py
quingo/backend/result_formatter.py
quingo/backend/symqc.py
quingo/backend/tianyan.py
quingo/backend/xiaohong.py
quingo/cim/__init__.py
quingo/cim/cim_sim.py
quingo/cim/parser.py
quingo/core/__init__.py
quingo/core/compile.py
quingo/core/compiler_config.py
quingo/core/data.py
quingo/core/data_transfer.py
quingo/core/exe_config.py
quingo/core/manager.py
quingo/core/preparation.py
quingo/core/quingo_logger.py
quingo/core/quingo_task.py
quingo/lib/__init__.py
quingo/lib/pyezQ.py
quingo/lib/qiskit_tools.py
quingo/lib/rem.py
quingo/lib/utils.py
quingo-0.4.3.dist-info/LICENSE
quingo-0.4.3.dist-info/METADATA
quingo-0.4.3.dist-info/WHEEL
quingo-0.4.3.dist-info/top_level.txt
quingo-0.4.3.dist-info/RECORD
