Metadata-Version: 2.1
Name: quingo
Version: 0.4.3
Summary: Quingo Runtime System
Home-page: https://gitee.com/quingo/quingo-runtime
Author: Xiang Fu
Author-email: gtaifu@gmail.com
Project-URL: Bug Tracker, https://gitee.com/quingo/quingo-runtime/issues
Classifier: Programming Language :: Python :: 3 :: Only
Classifier: License :: OSI Approved :: Apache Software License
Classifier: Operating System :: OS Independent
Requires-Python: >=3.7
License-File: LICENSE
Requires-Dist: numpy
Requires-Dist: scipy
Requires-Dist: pyqcisim (>=1.3.1)
Requires-Dist: symqc (>=1.1.1)
Requires-Dist: colorama
Requires-Dist: termcolor
Requires-Dist: requests
Requires-Dist: tqdm
Requires-Dist: pyquiet (>=0.0.4)
Requires-Dist: pycim-simulator
Requires-Dist: qualesim (>=1.0.2) ; sys_platform == "linux"
Requires-Dist: qualesim-tequila (>=1.0.2) ; sys_platform == "linux"
